{"nodes": [{"id": "root_index_html", "label": "index.html - Monto App Entry Point", "file_type": "code", "source_file": "index.html", "source_location": null, "source_url": null, "captured_at": null, "author": "Lovable", "contributor": null}], "edges": [{"source": "root_index_html", "target": "public_monto_icon", "relation": "references", "confidence": "EXTRACTED", "confidence_score": 1.0, "source_file": "index.html", "source_location": "line 8", "weight": 1.0}, {"source": "root_index_html", "target": "public_monto_og", "relation": "references", "confidence": "EXTRACTED", "confidence_score": 1.0, "source_file": "index.html", "source_location": "line 21", "weight": 1.0}, {"source": "root_index_html", "target": "concept_monto_brand", "relation": "references", "confidence": "EXTRACTED", "confidence_score": 1.0, "source_file": "index.html", "source_location": "line 14", "weight": 1.0}, {"source": "root_index_html", "target": "concept_react_vite_stack", "relation": "references", "confidence": "EXTRACTED", "confidence_score": 1.0, "source_file": "index.html", "source_location": "line 34", "weight": 1.0}], "hyperedges": []}